odoo/addons/delivery_schenker/README.rst
odoo/addons/delivery_schenker/__init__.py
odoo/addons/delivery_schenker/__manifest__.py
odoo/addons/delivery_schenker/api/fat_bookingWebServiceV1_1.wsdl
odoo/addons/delivery_schenker/api/fat_trackingWebServiceV2.wsdl
odoo/addons/delivery_schenker/api/prod_bookingWebServiceV1_1.wsdl
odoo/addons/delivery_schenker/api/prod_trackingWebServiceV2.wsdl
odoo/addons/delivery_schenker/data/delivery_schenker_data.xml
odoo/addons/delivery_schenker/i18n/delivery_schenker.pot
odoo/addons/delivery_schenker/i18n/es.po
odoo/addons/delivery_schenker/i18n/it.po
odoo/addons/delivery_schenker/models/__init__.py
odoo/addons/delivery_schenker/models/delivery_carrier.py
odoo/addons/delivery_schenker/models/product_packaging.py
odoo/addons/delivery_schenker/models/schenker_request.py
odoo/addons/delivery_schenker/models/stock_picking.py
odoo/addons/delivery_schenker/readme/CONFIGURE.rst
odoo/addons/delivery_schenker/readme/CONTRIBUTORS.rst
odoo/addons/delivery_schenker/readme/DESCRIPTION.rst
odoo/addons/delivery_schenker/readme/INSTALL.rst
odoo/addons/delivery_schenker/readme/ROADMAP.rst
odoo/addons/delivery_schenker/readme/USAGE.rst
odoo/addons/delivery_schenker/static/description/icon.png
odoo/addons/delivery_schenker/static/description/icon.svg
odoo/addons/delivery_schenker/static/description/index.html
odoo/addons/delivery_schenker/tests/__init__.py
odoo/addons/delivery_schenker/tests/common.py
odoo/addons/delivery_schenker/tests/test_delivery_schenker.py
odoo/addons/delivery_schenker/views/delivery_schenker_view.xml
odoo/addons/delivery_schenker/views/stock_picking_views.xml
odoo14_addon_delivery_schenker-14.0.2.2.0.dist-info/METADATA
odoo14_addon_delivery_schenker-14.0.2.2.0.dist-info/WHEEL
odoo14_addon_delivery_schenker-14.0.2.2.0.dist-info/top_level.txt
odoo14_addon_delivery_schenker-14.0.2.2.0.dist-info/RECORD
